anyvoice/__init__.py
anyvoice/base.py
anyvoice/log.py
anyvoice/providers/__init__.py
anyvoice/providers/edge.py
anyvoice/providers/openai.py
anyvoice/py.typed
anyvoice/sinks.py
anyvoice/stream.py
anyvoice-0.0.2.dist-info/licenses/LICENSE
anyvoice-0.0.2.dist-info/WHEEL
anyvoice-0.0.2.dist-info/METADATA
anyvoice-0.0.2.dist-info/RECORD
