Metadata-Version: 2.4
Name: anyvoice
Version: 0.0.2
Summary: Common interface for streaming tts providers
Keywords: 
Author: Philipp Temminghoff
Author-email: Philipp Temminghoff <philipptemminghoff@googlemail.com>
License-Expression: MIT
License-File: LICENSE
Classifier: Development Status :: 4 - Beta
Classifier: Framework :: Pydantic
Classifier: Framework :: Pydantic :: 2
Classifier: Intended Audience :: Developers
Classifier: Operating System :: OS Independent
Classifier: Programming Language :: Python :: 3
Classifier: Programming Language :: Python :: 3 :: Only
Classifier: Programming Language :: Python :: 3.12
Classifier: Programming Language :: Python :: 3.13
Classifier: Programming Language :: Python :: 3.14
Classifier: Topic :: Documentation
Classifier: Topic :: Software Development
Classifier: Topic :: Utilities
Classifier: Typing :: Typed
Requires-Dist: pydantic
Requires-Dist: schemez
Requires-Dist: openai>=1.0.0 ; extra == 'openai'
Requires-Dist: sounddevice>=0.5.0 ; extra == 'openai'
Requires-Dist: numpy>=1.24.0 ; extra == 'openai'
Requires-Dist: edge-tts>=7.0.0 ; extra == 'tts-edge'
Requires-Dist: miniaudio>=1.60 ; extra == 'tts-edge'
Requires-Dist: sounddevice>=0.5.0 ; extra == 'tts-edge'
Requires-Python: >=3.13
Project-URL: Code coverage, https://app.codecov.io/gh/phil65/anyvoice
Project-URL: Discussions, https://github.com/phil65/anyvoice/discussions
Project-URL: Documentation, https://phil65.github.io/anyvoice/
Project-URL: Issues, https://github.com/phil65/anyvoice/issues
Project-URL: Source, https://github.com/phil65/anyvoice
Provides-Extra: openai
Provides-Extra: tts-edge
